{
	"name": "Boss",
	"layers": [
		{
			"name": "Boss",
			"overriden": 0,
			"subLayers": [],
			"instances": [
				{
					"type": "Background3",
					"properties": {
						"initially-visible": true,
						"initial-animation": "Default",
						"initial-frame": 0,
						"enable-collisions": true,
						"live-preview": false
					},
					"uid": 14,
					"sid": 489948183185169,
					"tags": "",
					"instanceVariables": {},
					"behaviors": {},
					"instanceFolderItem": {
						"sid": 489948183185169,
						"expanded": true,
						"folderName": "",
						"indexInFolder": -1,
						"folderNestingLevel": -1
					},
					"showing": true,
					"locked": false,
					"world": {
						"x": 294,
						"y": 540,
						"width": 1120,
						"height": 1161,
						"originX": 0.5,
						"originY": 0.5,
						"color": [
							1,
							1,
							1,
							1
						],
						"angle": 0,
						"zElevation": 0
					}
				},
				{
					"type": "boss",
					"properties": {
						"initially-visible": true,
						"initial-animation": "Animation 1",
						"initial-frame": 0,
						"enable-collisions": true,
						"live-preview": false
					},
					"uid": 9,
					"sid": 884058007214102,
					"tags": "",
					"instanceVariables": {
						"Vida": 400,
						"vida_max": 400
					},
					"behaviors": {
						"Torreta": {
							"properties": {
								"range": 500,
								"rate-of-fire": 10,
								"rotate": true,
								"rotate-speed": 100,
								"target-mode": "first-in-range",
								"predictive-aim": false,
								"projectile-speed": 500,
								"use-collision-cells": true,
								"enabled": true
							}
						},
						"Sólido": {
							"properties": {
								"enabled": true,
								"tags": ""
							}
						},
						"Seno": {
							"properties": {
								"movement": "horizontal",
								"wave": "sine",
								"period": 4,
								"period-random": 0,
								"period-offset": 0,
								"period-offset-random": 0,
								"magnitude": 150,
								"magnitude-random": 0,
								"enabled": true,
								"live-preview": false
							}
						}
					},
					"instanceFolderItem": {
						"sid": 884058007214102,
						"expanded": true,
						"folderName": "",
						"indexInFolder": -1,
						"folderNestingLevel": -1
					},
					"showing": true,
					"locked": false,
					"world": {
						"x": 241,
						"y": 287,
						"width": 226,
						"height": 226,
						"originX": 0.4765625,
						"originY": 0.8359375,
						"color": [
							1,
							1,
							1,
							1
						],
						"angle": 0,
						"zElevation": 0
					}
				},
				{
					"type": "jug_boss",
					"properties": {
						"initially-visible": true,
						"initial-animation": "Animation 1",
						"initial-frame": 0,
						"enable-collisions": true,
						"live-preview": false
					},
					"uid": 10,
					"sid": 666293007806090,
					"tags": "",
					"instanceVariables": {},
					"behaviors": {
						"8Direcciones": {
							"properties": {
								"max-speed": 350,
								"acceleration": 800,
								"deceleration": 500,
								"directions": "dir-8",
								"set-angle": "smooth",
								"allow-sliding": false,
								"default-controls": true,
								"enabled": true
							}
						},
						"Bala": {
							"properties": {
								"speed": 100,
								"acceleration": 0,
								"gravity": 0,
								"bounce-off-solids": false,
								"set-angle": true,
								"step": false,
								"enabled": true
							}
						},
						"RestringidoALaEscena": {
							"properties": {
								"bound-by": "edge"
							}
						}
					},
					"instanceFolderItem": {
						"sid": 666293007806090,
						"expanded": true,
						"folderName": "",
						"indexInFolder": -1,
						"folderNestingLevel": -1
					},
					"showing": true,
					"locked": false,
					"world": {
						"x": 241,
						"y": 1065,
						"width": 128,
						"height": 128,
						"originX": 0.5,
						"originY": 0.5,
						"color": [
							1,
							1,
							1,
							1
						],
						"angle": 0,
						"zElevation": 0
					}
				},
				{
					"type": "barradeVida",
					"properties": {
						"initially-visible": true,
						"initial-animation": "Animation 1",
						"initial-frame": 0,
						"enable-collisions": true,
						"live-preview": false
					},
					"uid": 13,
					"sid": 386208143232867,
					"tags": "",
					"instanceVariables": {},
					"behaviors": {
						"Ancla": {
							"properties": {
								"left-edge": "window-left",
								"top-edge": "window-top",
								"right-edge": "none",
								"bottom-edge": "none",
								"enabled": true
							}
						}
					},
					"instanceFolderItem": {
						"sid": 386208143232867,
						"expanded": true,
						"folderName": "",
						"indexInFolder": -1,
						"folderNestingLevel": -1
					},
					"showing": true,
					"locked": false,
					"world": {
						"x": 244,
						"y": 85,
						"width": 400,
						"height": 50,
						"originX": 0.5,
						"originY": 0.5,
						"color": [
							1,
							1,
							1,
							1
						],
						"angle": 0,
						"zElevation": 0
					}
				},
				{
					"type": "disp_boss",
					"properties": {
						"initially-visible": true,
						"initial-animation": "Animation 1",
						"initial-frame": 0,
						"enable-collisions": true,
						"live-preview": false
					},
					"uid": 17,
					"sid": 644798464341411,
					"tags": "",
					"instanceVariables": {},
					"behaviors": {
						"Físicas": {
							"properties": {
								"immovable": false,
								"collision-mask": "use-collision-polygon",
								"prevent-rotation": false,
								"density": 1,
								"friction": 0.5,
								"elasticity": 0.2,
								"linear-damping": 0,
								"angular-damping": 0.01,
								"bullet": true,
								"enabled": true
							}
						}
					},
					"instanceFolderItem": {
						"sid": 644798464341411,
						"expanded": true,
						"folderName": "",
						"indexInFolder": -1,
						"folderNestingLevel": -1
					},
					"showing": true,
					"locked": false,
					"world": {
						"x": 714,
						"y": 258,
						"width": 32,
						"height": 32,
						"originX": 0.5,
						"originY": 0.5,
						"color": [
							1,
							1,
							1,
							1
						],
						"angle": 0,
						"zElevation": 0
					}
				},
				{
					"type": "JEFE_DERROTADO",
					"properties": {
						"text": "PRIMER JEFE ENEMIGO DERROTADO",
						"enable-bbcode": true,
						"font": "OCR A",
						"size": 25,
						"line-height": 0,
						"bold": false,
						"italic": false,
						"color": [
							0.29411764705882354,
							0.9803921568627451,
							0,
							1
						],
						"horizontal-alignment": "center",
						"vertical-alignment": "center",
						"wrapping": "word",
						"text-direction": "ltr",
						"icon-set": -1,
						"initially-visible": true,
						"origin": "top-left",
						"read-aloud": false
					},
					"uid": 23,
					"sid": 417350282721995,
					"tags": "",
					"instanceVariables": {},
					"behaviors": {},
					"instanceFolderItem": {
						"sid": 417350282721995,
						"expanded": true,
						"folderName": "",
						"indexInFolder": -1,
						"folderNestingLevel": -1
					},
					"showing": true,
					"locked": false,
					"world": {
						"x": 114,
						"y": 438,
						"width": 274,
						"height": 134,
						"originX": 0,
						"originY": 0,
						"color": [
							1,
							1,
							1,
							0
						],
						"angle": 0,
						"zElevation": 0
					}
				},
				{
					"type": "ast2",
					"properties": {
						"initially-visible": true,
						"initial-animation": "Animation 1",
						"initial-frame": 0,
						"enable-collisions": true,
						"live-preview": false
					},
					"uid": 29,
					"sid": 282887630834957,
					"tags": "",
					"instanceVariables": {},
					"behaviors": {
						"Sólido": {
							"properties": {
								"enabled": true,
								"tags": ""
							}
						},
						"Físicas": {
							"properties": {
								"immovable": false,
								"collision-mask": "use-collision-polygon",
								"prevent-rotation": false,
								"density": 0.1,
								"friction": 100,
								"elasticity": 0,
								"linear-damping": 0,
								"angular-damping": 0.01,
								"bullet": false,
								"enabled": true
							}
						}
					},
					"instanceFolderItem": {
						"sid": 282887630834957,
						"expanded": true,
						"folderName": "",
						"indexInFolder": -1,
						"folderNestingLevel": -1
					},
					"showing": true,
					"locked": false,
					"world": {
						"x": 671,
						"y": 87,
						"width": 64,
						"height": 64,
						"originX": 0.5,
						"originY": 0.5,
						"color": [
							1,
							1,
							1,
							1
						],
						"angle": 0,
						"zElevation": 0
					}
				},
				{
					"type": "exterminador",
					"properties": {
						"text": "EXTERMINADOR",
						"enable-bbcode": true,
						"character-width": 16,
						"character-height": 16,
						"character-set": "ABCDEFGHIJKLMNOPQRSTUVWXYZabcdefghijklmnopqrstuvwxyz0123456789.,;:?!-_~#\"'&()[]|`\\/@°+=*$£€<>",
						"spacing-data": "",
						"scale": 1,
						"character-spacing": 0,
						"line-height": 0,
						"horizontal-alignment": "center",
						"vertical-alignment": "center",
						"wrapping": "word",
						"initially-visible": true,
						"origin": "top-left",
						"read-aloud": false
					},
					"uid": 25,
					"sid": 825343808287907,
					"tags": "",
					"instanceVariables": {},
					"behaviors": {},
					"instanceFolderItem": {
						"sid": 825343808287907,
						"expanded": true,
						"folderName": "",
						"indexInFolder": -1,
						"folderNestingLevel": -1
					},
					"showing": true,
					"locked": false,
					"world": {
						"x": 149,
						"y": 14,
						"width": 208,
						"height": 28,
						"originX": 0,
						"originY": 0,
						"color": [
							0.9882352941176471,
							0.011764705882352941,
							0.011764705882352941,
							0
						],
						"angle": 0,
						"zElevation": 0
					}
				},
				{
					"type": "reintentarboss",
					"properties": {
						"text": "PRESIONE R PARA REINTENTAR",
						"enable-bbcode": true,
						"character-width": 16,
						"character-height": 16,
						"character-set": "ABCDEFGHIJKLMNOPQRSTUVWXYZabcdefghijklmnopqrstuvwxyz0123456789.,;:?!-_~#\"'&()[]|`\\/@°+=*$£€<>",
						"spacing-data": "",
						"scale": 1,
						"character-spacing": 0,
						"line-height": 0,
						"horizontal-alignment": "center",
						"vertical-alignment": "center",
						"wrapping": "word",
						"initially-visible": true,
						"origin": "top-left",
						"read-aloud": false
					},
					"uid": 31,
					"sid": 396538205003162,
					"tags": "",
					"instanceVariables": {},
					"behaviors": {},
					"instanceFolderItem": {
						"sid": 396538205003162,
						"expanded": true,
						"folderName": "",
						"indexInFolder": -1,
						"folderNestingLevel": -1
					},
					"showing": true,
					"locked": false,
					"world": {
						"x": 42,
						"y": 912,
						"width": 433,
						"height": 27,
						"originX": 0,
						"originY": 0,
						"color": [
							1,
							0.09803921568627451,
							0,
							0
						],
						"angle": 0,
						"zElevation": 0
					}
				},
				{
					"type": "exppro",
					"properties": {
						"initially-visible": true,
						"initial-animation": "Animación 1",
						"initial-frame": 0,
						"enable-collisions": true,
						"live-preview": false
					},
					"uid": 32,
					"sid": 215412977958313,
					"tags": "",
					"instanceVariables": {},
					"behaviors": {},
					"instanceFolderItem": {
						"sid": 215412977958313,
						"expanded": true,
						"folderName": "",
						"indexInFolder": -1,
						"folderNestingLevel": -1
					},
					"showing": true,
					"locked": false,
					"world": {
						"x": 684,
						"y": 956,
						"width": 128,
						"height": 128,
						"originX": 0.5,
						"originY": 0.5,
						"color": [
							1,
							1,
							1,
							1
						],
						"angle": 0,
						"zElevation": 0
					}
				}
			],
			"sid": 718744621985840,
			"effectTypes": [],
			"isInitiallyVisible": true,
			"isInitiallyInteractive": true,
			"isHTMLElementsLayer": false,
			"color": [
				1,
				1,
				1,
				1
			],
			"backgroundColor": [
				1,
				1,
				1,
				1
			],
			"isTransparent": false,
			"parallaxX": 1,
			"parallaxY": 1,
			"scaleRate": 1,
			"forceOwnTexture": false,
			"renderingMode": "3d",
			"drawOrder": "z-order",
			"useRenderCells": false,
			"blendMode": "normal",
			"zElevation": 0,
			"global": false
		}
	],
	"scene-graphs-folder-root": {
		"items": [],
		"subfolders": []
	},
	"sid": 990233948639864,
	"nonworld-instances": [],
	"effectTypes": [],
	"width": 500,
	"height": 1000,
	"unboundedScrolling": false,
	"vpX": 0.5,
	"vpY": 0.5,
	"projection": "perspective",
	"eventSheet": "Eventos - Boss"
}